{
  "title": "Home",
  "metadescription": "Test CA",
  "background": {
    "src": "/media/background.png",
    "alt": "MOT architecture logo",
    "isP5enabled": false
  },
  "projects": [
    {
      "images": [
        {
          "src": "/media/casa-mosaic_page-0001.jpg"
        }
      ],
      "row": 4,
      "column": 3,
      "size": "large",
      "title": "Casa Mosaic",
      "date": "2025-05",
      "subtitle": "\\-"
    },
    {
      "images": [
        {
          "src": "/media/vistes-biombo-ombres_page-0001-1-.jpg"
        }
      ],
      "row": 9,
      "column": 2,
      "size": "medium",
      "title": "Biombo Casa Orlandai",
      "date": "2025-05",
      "subtitle": "\\-"
    },
    {
      "title": "The everyday performance",
      "size": "medium",
      "row": 2,
      "column": 5,
      "images": [
        {
          "src": "/media/esquema-andami_page-0001.jpg"
        }
      ],
      "date": "2025-05",
      "subtitle": "\\-"
    }
  ],
  "contact": {
    "image": {
      "src": "/media/untitled-2.jpg",
      "alt": "equip"
    },
    "text": "Bernat Renau Oliveras, Víctor Rufart Gimeno i Gemma Vives Soler \n\nCarrer Jaén 6, 08012, Barcelona"
  }
}
